{
  "response": [
    {
        "maintainer": ["darkphnx", "Roxor007"],
        "support_group": "https://t.me/drkphnxsp",
        "oem": "Xiaomi",
        "device": "alioth",
        "device_name": "Poco F3/Redmi K40/Mi 11x",
        "filename": "Matrixx-v11.2.5-Official-alioth-Gapps-202502280239.zip",
        "download": "https://sourceforge.net/projects/projectmatrixx/files/Android-15/alioth/Matrixx-v11.2.5-Official-alioth-Gapps-202502280239.zip/download",
        "timestamp": 1740710349,
        "md5": "565a9584eb7b1ec4df54032df69450d5",
        "size": 2399168266,
        "version": "11.2.5"
    }
  ]
}
